Tarea 1/tester.v
 module tester (
    output reg clk, //Senial de reloj
    output reg rst, //Senial de reinicio
    output reg sensor_vehicule, //Sensor de vehiculo
    output reg sensor_moved_vehicule, //Sensor de vehiculo desplazado
    output wire [15:0] correct_password, //Contrasenia correcta
    output reg [15:0] password_input, //Contrasenia de entrada
    input wire open_gate, // Salida compuerta abierta
    input wire close_gate, // Salida compuerta cerrada
    input wire alarm_wrong_pin, // Salida alarma de pin incorrecto
    input wire alarm_blocked // Salida alarma bloqueo
);
    
    // Generación del reloj
    initial begin
        clk = 0;
        forever #5 clk = ~clk;
    end

        // Secuencia de prueba
    initial begin

        rst = 1; sensor_vehicule = 0; sensor_moved_vehicule = 0; password_input = 0;
        #10 rst = 0;

        //Prueba 1: Ingreso de clave correcta
        #10 sensor_vehicule = 1; //Llega vehiculo
        #20 password_input = 16'b0011_0111_0110_0001; //Ingreso contrasenia correcta
        #10 sensor_moved_vehicule = 1;//Vehiculo se mueve
        #10 sensor_moved_vehicule = 0;//Vehiculo ya no se mueve
        #10 sensor_vehicule = 0;//Ya no hay vehiculo

        //Prueba 2: Ingreso de clave incorrecta 2 veces contrasenia
        #10 sensor_vehicule = 1; //Llega vehiculo
        #10 password_input = 16'b0001_0010_0011_0101; // Contrasenia incorrecta
        #10 sensor_vehicule = 1; //
        #10 password_input = 16'b0001_0010_0011_0100; // Contrasenia incorrecta
        #10 sensor_vehicule = 1;
        #10 password_input = 16'b0011_0111_0110_0001; // Contrasenia correcta
        #10 sensor_vehicule = 1;
        #10 sensor_moved_vehicule = 1; //Se mueve vehiculo
        #10 sensor_moved_vehicule = 0; //Ya no se mueve vehiculo
        #10 sensor_vehicule = 0; //Ya no hay vehiculo

        // Prueba 3: Ingreso de clave incorrecta 3 veces
        #10 sensor_vehicule = 1; //Llega vehiculo
        #10 password_input = 16'b0001_0010_0011_0101; // constrasenia incorrecta
        #10 sensor_vehicule = 1;
        #10 sensor_vehicule = 1;
        #10 password_input = 16'b0001_0010_0011_0100; // constrasenia incorrecta
        #10 sensor_vehicule = 1;
        #10 sensor_vehicule = 1;
        #10 password_input = 16'b0001_0011_0110_1000; // constrasenia incorrecta
        
        // Prueba 4: Activación simultánea de ambos sensores
        #50 sensor_vehicule = 1; sensor_moved_vehicule = 1;
        #10 sensor_vehicule = 1;
        #10 rst = 1;//Se activa el reset
        #10 rst = 0;
        #10 sensor_moved_vehicule = 0;
        //Se prueba de nuevo el funcionamiento del sistema
        #10 sensor_vehicule = 1; //Llega vehiculo
        #20 password_input = 16'b0011_0111_0110_0001; //Ingreso contrasenia correcta
        #10 sensor_moved_vehicule = 1;//Vehiculo se mueve
        #10 sensor_moved_vehicule = 0;//Vehiculo ya no se mueve
        #10 sensor_vehicule = 0;//Ya no hay vehiculo
        #10 $finish;
    end
endmodule

Tarea 1/controlador.v
module controlador_estacionamiento (
    input wire clk, //Senial de reloj
    input wire rst, //Senial de reinicio
    input wire sensor_vehicule, //Sensor de vehiculo
    input wire sensor_moved_vehicule, //Sensor de vehiculo desplazado
    //input wire [15:0] correct_password, //Contrasenia correcta
    input wire [15:0] password_input, //Contrasenia de entrada
    output reg open_gate, // Salida compuerta abierta
    output reg close_gate, // Salida compuerta cerrada
    output reg alarm_wrong_pin, // Salida alarma de pin incorrecto
    output reg alarm_blocked // Salida alarma bloqueo
);

    //Definicion de los estados del conrolador de estacionamiento
    parameter IDLE = 3'b000;//Estado inicial
    parameter WAIT_FOR_KEY = 3'b001;//Espera de contrasenia
    parameter CHECK_KEY = 3'b010;//Verificacion contrasenia
    parameter OPEN_GATE = 3'b011;//Abrir compuerta
    parameter CLOSE_GATE = 3'b100;//Cerrar compuerta
    parameter WRONG_KEY = 3'b101;//Clave erronea
    parameter BLOCKED = 3'b110;//Alarma bloqueo

    //Contrasenia por defecto
    parameter correct_password = 16'b0010_0100_0110_1000;//2468
    reg [2:0] state, next_state; //registros del estado actual y siguiente estado
    reg [2:0] counter; // Contador para intentos fallidos

    //Transición de estados
    always @(posedge clk or posedge rst) begin
        if (rst) begin //Caso inicial y de reinicio, se establecen condiciones iniciales
            state <= IDLE; //Se establce como estado inicial IDLE
            counter <= 0;//reinicio contador
            open_gate <= 0;
            close_gate <= 0;
            alarm_wrong_pin <= 0;
            alarm_blocked <= 0;
        end else begin
            state <= next_state; //Caso actual para a ser el siguiente estado
        end
    end

    //máquina de estados
    always @(*) begin
        next_state = state;//Siguiente estado es el estado actual
        case (state)
            IDLE: begin //Caso inicial maquina estados
                if (sensor_vehicule) begin //Si detecto un vehiculo
                    next_state = WAIT_FOR_KEY;//Espero contrasenia
                end
            end
    
            WAIT_FOR_KEY: begin //Caso donde espero contrasenia
                next_state = CHECK_KEY; //Verifico contrasenia
            end
            
            CHECK_KEY: begin //Caso donde verifico contrasenia
                if (password_input == correct_password) begin //Contrsenia correcta
                    next_state = OPEN_GATE; //Abro compuerta
                end else begin //Contrasenia incorrecta
                    next_state = WRONG_KEY;
                end
            end
            
            OPEN_GATE: begin //Caso donde abro compuerta
                if (sensor_moved_vehicule) begin //Verifico si el vehiculo se mueve
                    next_state = CLOSE_GATE; //Cierro compuerta
                end
            end
            
            CLOSE_GATE: begin //Caso donde se cierra compuerta
                next_state = IDLE; //Regreso a estado inicial en espera de un vehiculo
            end
            
            WRONG_KEY: begin //Caso de clave erronea
                if (counter >= 3) begin // Si el contador de intentos es mayor igual a  3
                    next_state = BLOCKED; //Activo alarma de bloqueo
                end else begin //Caso contrario pido que se ingrese contrasenia correcta
                    next_state = WAIT_FOR_KEY;
                end
            end
            
            BLOCKED: begin
                //Permanezco bloqueado hasta reiniciar sistema
            end
        endcase
    end

    //Comportamiento salidas controlador, siempre que exista un cambio
    always @(posedge clk or posedge rst) begin
        if (rst) begin
            open_gate <= 0;
            close_gate <= 0;
            alarm_wrong_pin <= 0;
            alarm_blocked <= 0;
            counter <= 0;
        end else begin
            case (state)//Comportamiento de las salidas ante cambios de estados
                IDLE: begin //Caso inicial
                    open_gate <= 0;
                    close_gate <= 0;
                    alarm_wrong_pin <= 0;
                    alarm_blocked <= 0;
                    counter <= 0;
                end
                
                WAIT_FOR_KEY: begin 
                    //Espero clave
                end
                
                CHECK_KEY: begin
                    //Verifico clave
                end
                
                OPEN_GATE: begin //Abro compuerta
                    open_gate <= 1;//Abro puerta
                    close_gate <= 0;//puerta abierta
                    alarm_wrong_pin <= 0;//No bloqueo
                    alarm_blocked <= 0;//No bloqueo
                end
                
                CLOSE_GATE: begin //Cierro puerta
                    open_gate <= 0;
                    close_gate <= 1;
                end
                
                WRONG_KEY: begin //Caso de introducir mal la contrasenia
                    counter <= counter + 1; //Cuenta un intento
                    if (counter > 2) begin //Verifico si llego a 3 intentos
                        alarm_wrong_pin <= 1; //Activo alarma de pin incorrecto
                    end
                end
                
                BLOCKED: begin //Alarma de bloqueo
                    alarm_blocked <= 1; //activo alarma
                end
            endcase
        end
    end
endmodule

Tarea 1/testbench.v
`include "controlador.v"
`include "tester.v"

module controlador_estacionamiento_tb;
//Seniales para conectar el tester con el device under teste
    wire clk;
    wire rst;
    wire sensor_vehicule;
    wire sensor_moved_vehicule;
    wire [15:0] password_input;
    wire open_gate;
    wire close_gate;
    wire alarm_wrong_pin;
    wire alarm_blocked;

    //Clave correcta 3761
    //wire [15:0] correct_password = 16'b0011_0111_0110_0001;
    
    //Se crea un archivo resultados.vcd para abrir en gtkwave con las varibales del controlador de estacionamientos
    initial begin
        $dumpfile("resultados.vcd");
        $dumpvars(-1, U0);
    end

    // Instancia del modulo controlador, //Clave correcta 3761 16'b0011_0111_0110_0001
    controlador_estacionamiento #(.correct_password(16'b0011_0111_0110_0001)) U0 (
        .clk(clk),
        .rst(rst),
        .sensor_vehicule(sensor_vehicule),
        .sensor_moved_vehicule(sensor_moved_vehicule),
        .password_input(password_input),
        //.correct_password(correct_password),
        .open_gate(open_gate),
        .close_gate(close_gate),
        .alarm_wrong_pin(alarm_wrong_pin),
        .alarm_blocked(alarm_blocked)
    );
    
    // Instancia del modulo tester
    tester T0 (
        .clk(clk),
        .rst(rst),
        .sensor_vehicule(sensor_vehicule),
        .sensor_moved_vehicule(sensor_moved_vehicule),
        .password_input(password_input),
        //.correct_password(correct_password),
        .open_gate(open_gate),
        .close_gate(close_gate),
        .alarm_wrong_pin(alarm_wrong_pin),
        .alarm_blocked(alarm_blocked)
    );
endmodule

Tarea 1/resultados.vcd
$date
	Fri Sep 06 07:58:25 2024
$end
$version
	Icarus Verilog
$end
$timescale
	1s
$end
$scope module controlador_estacionamiento_tb $end
$scope module U0 $end
$var wire 1 ! clk $end
$var wire 16 " password_input [15:0] $end
$var wire 1 # rst $end
$var wire 1 $ sensor_moved_vehicule $end
$var wire 1 % sensor_vehicule $end
$var reg 1 & alarm_blocked $end
$var reg 1 ' alarm_wrong_pin $end
$var reg 1 ( close_gate $end
$var reg 3 ) counter [2:0] $end
$var reg 3 * next_state [2:0] $end
$var reg 1 + open_gate $end
$var reg 3 , state [2:0] $end
$upscope $end
$upscope $end
$enddefinitions $end
#0
$dumpvars
b0 ,
0+
b0 *
b0 )
0(
0'
0&
0%
0$
1#
b0 "
0!
$end
#5
1!
#10
0!
0#
#15
1!
#20
b1 *
0!
1%
#25
b10 *
b1 ,
1!
#30
0!
#35
b101 *
b10 ,
1!
#40
b11 *
0!
b11011101100001 "
#45
b11 ,
1!
#50
b100 *
0!
1$
#55
b0 *
b100 ,
1+
1!
#60
b0 *
0!
0$
#65
b1 *
1(
0+
b0 ,
1!
#70
b0 *
0!
0%
#75
0(
1!
#80
b1 *
0!
1%
#85
b10 *
b1 ,
1!
#90
b10 *
0!
b1001000110101 "
#95
b101 *
b10 ,
1!
#100
0!
#105
b1 *
b101 ,
1!
#110
b1 *
0!
b1001000110100 "
#115
b10 *
b1 ,
b1 )
1!
#120
0!
#125
b101 *
b10 ,
1!
#130
b11 *
0!
b11011101100001 "
#135
b11 ,
1!
#140
0!
#145
1+
1!
#150
b100 *
0!
1$
#155
b0 *
b100 ,
1!
#160
b0 *
0!
0$
#165
b1 *
1(
0+
b0 ,
1!
#170
b0 *
0!
0%
#175
b0 )
0(
1!
#180
b1 *
0!
1%
#185
b10 *
b1 ,
1!
#190
b10 *
0!
b1001000110101 "
#195
b101 *
b10 ,
1!
#200
0!
#205
b1 *
b101 ,
1!
#210
0!
#215
b10 *
b1 ,
b1 )
1!
#220
b10 *
0!
b1001000110100 "
#225
b101 *
b10 ,
1!
#230
0!
#235
b1 *
b101 ,
1!
#240
0!
#245
b10 *
b10 )
b1 ,
1!
#250
b10 *
0!
b1001101101000 "
#255
b101 *
b10 ,
1!
#260
0!
#265
b1 *
b101 ,
1!
#270
0!
#275
b10 *
b1 ,
b11 )
1!
#280
0!
#285
b101 *
b10 ,
1!
#290
0!
#295
b110 *
b101 ,
1!
#300
b110 *
0!
1$
#305
1'
b100 )
b110 ,
1!
#310
0!
#315
1&
1!
#320
b1 *
0&
0'
b0 )
b0 ,
0!
1#
#325
1!
#330
0!
0#
#335
b10 *
b1 ,
1!
#340
b10 *
0!
0$
#345
b101 *
b10 ,
1!
#350
0!
#355
b1 *
b101 ,
1!
#360
0!
#365
b10 *
b1 ,
b1 )
1!
#370
b10 *
0!
b11011101100001 "
#375
b11 *
b10 ,
1!
#380
b11 *
0!
1$
#385
b100 *
b11 ,
1!
#390
b11 *
0!
0$
#395
1+
1!
#400
0!
0%
