Tarea3/src/tester.v
module tester(
    output reg clk,
    output reg rst,
    output reg TARJETA_RECIBIDA,
    output reg TIPO_TRANS,
    output reg MONTO_STB,
    output reg DIGITO_STB,
    output reg [3:0] DIGITO,
    output reg [15:0] PIN,
    output reg [31:0] MONTO,
    output reg [63:0] BALANCE_INICIAL,
    input wire BALANCE_ACTUALIZADO,
    input wire ENTREGAR_DINERO,
    input wire PIN_INCORRECTO,
    input wire ADVERTENCIA,
    input wire BLOQUEO,
    input wire FONDOS_INSUFICIENTES
);

    // Generación de señal de reloj (clk)
    initial clk = 0;
    always #5 clk = ~clk; // Reloj de periodo 10 unidades de tiempo

    // Proceso de pruebas
    // Inicialización de señales
    initial begin
        // Reset inicial
        rst = 1;
        TARJETA_RECIBIDA = 0;
        TIPO_TRANS = 0;
        MONTO_STB = 0;
        DIGITO_STB = 0;
        DIGITO = 0;
        PIN = 16'b0011_0111_0110_0001; // PIN correcto: 3761
        MONTO = 0;
        BALANCE_INICIAL = 64'd10000; // Balance inicial: 10,000
        #10 rst = 0;

        // Simulación de insertar tarjeta
        #10 TARJETA_RECIBIDA = 1;

        // Simulación de ingreso de PIN correcto
        #20 DIGITO = 4'd3; DIGITO_STB = 1;
        #10 DIGITO_STB = 0;
        #20 DIGITO = 4'd7; DIGITO_STB = 1;
        #10 DIGITO_STB = 0;
        #20 DIGITO = 4'd6; DIGITO_STB = 1;
        #10 DIGITO_STB = 0;
        #20 DIGITO = 4'd1; DIGITO_STB = 1;
        #10 DIGITO_STB = 0;

        // Espera para verificar el PIN
        //#30;

        // Simulación de seleccionar deposito (TIPO_TRANS = 0) y monto
        #10 TIPO_TRANS = 0; MONTO = 32'd2000; MONTO_STB = 1;
        #20 MONTO_STB = 0;

        // Espera para procesar el retiro
        #50;

        // Simulación de insertar un PIN incorrecto
        #100 rst = 1; #10 rst = 0; // Resetear para la siguiente prueba
        #20 TARJETA_RECIBIDA = 1;
        #20 DIGITO = 4'd1; DIGITO_STB = 1;
        #10 DIGITO_STB = 0;
        #20 DIGITO = 4'd1; DIGITO_STB = 1;
        #10 DIGITO_STB = 0;
        #20 DIGITO = 4'd1; DIGITO_STB = 1;
        #10 DIGITO_STB = 0;
        #20 DIGITO = 4'd1; DIGITO_STB = 1;
        #10 DIGITO_STB = 0;

        // Espera para verificar el PIN incorrecto
        #30;

        // Simulación de repetir PIN incorrecto dos veces más
        #50;
        #20 DIGITO = 4'd2; DIGITO_STB = 1;
        #10 DIGITO_STB = 0;
        #20 DIGITO = 4'd2; DIGITO_STB = 1;
        #10 DIGITO_STB = 0;
        #20 DIGITO = 4'd2; DIGITO_STB = 1;
        #10 DIGITO_STB = 0;
        
        // Verificar que el sistema se bloquee después del tercer intento
        #50;

        // Fin de la simulación
        #500 $finish;
    end

endmodule

Tarea3/src/cajeroAutomatico.v
module cajero_automatico (
    //Entradas
    input wire clk, //Senial de reloj
    input wire rst, //Senial de reinicio
    input wire TARJETA_RECIBIDA, //Senial tarjeta recibida
    input wire TIPO_TRANS, //Senial tipo transacion 0 desposito 1 retiro
    input wire MONTO_STB, // Senial de entrada que se pone en 1 durante un solo ciclo de reloj (STB) cuando se ha actualizado el valor del MONTO a través del teclado
    input wire DIGITO_STB, //Senial de entrada que se pone en 1 durante un solo ciclo de reloj (STB) cuando se presiona un botón en el teclado. La lectura del PIN debe compararse con los valores de la entrada DIGITO cuando DIGITO_STB=1.
    input wire [3:0] DIGITO, // Ultimo dígito tecleado por el usuario
    input wire [15:0] PIN, //Entrada de 16 bits donde cada grupo de 4 bits representa un dígito del PIN de la tarjeta que se recibió
    input wire [31:0] MONTO, //Entrada de 32 bits que representa el monto de la transacción expresado en binario.
    input wire [63:0] BALANCE_INICIAL, //Entrada de 64 bits que contiene el balance de la cuenta al inicio de cada transacción. Debe tener su valor actualizado al momento en que se digita el pin correcto. Se debe garantizar que el banco de pruebas se ajuste a este comportamiento. 
    //Salidas
    output reg BALANCE_ACTUALIZADO, //Salida de un bit para indicar que una transacción fue exitosa y que se actualizó el balance en la cuenta, tanto para depósitos como para retiros
    output reg ENTREGAR_DINERO, // Salida de un bit para indicarle al cajero que entregue el MONTO durante una transacción de retiro
    output reg PIN_INCORRECTO, // Senial que indica que el valor del PIN recibido a través del teclado (la entrada DIGITO) es distinto del PIN de la tarjeta especificado en la entrada PIN.
    output reg ADVERTENCIA, // Salida binaria que se enciende cuando el usuario ha introducido el PIN de forma incorrecta dos veces 
    output reg BLOQUEO,//Salida binaria que se enciende cuando el usuario ha introducido el pin de forma incorrecta 3 veces
    output reg FONDOS_INSUFICIENTES // Senial salida cuando no hay suficientes fondos
);

    //Definicion de los estados del cajero automatico
    parameter IDLE = 0;//Estado inicial
    parameter ESPERA_TARJETA = 1;//Espera de tarjeta
    parameter LEER_PIN = 2; //Lectura de pin
    parameter VERIFICAR_PIN = 3;//Verificacion pin
    parameter SELECCIONAR_TRANSACCION = 4;//Seleciono tipo transacion
    parameter PROCESAR_DEPOSITO = 5;//Proceso un deposito
    parameter PROCESAR_RETIRO = 6;//Proceso un retiro
    parameter JUMP_IDLE = 7;
    parameter WRONG_PIN  = 8;//Pin incorrecto
    parameter BLOCKED = 9;//Bloqueo sistema cuando e cuando el usuario ha introducido el pin de forma incorrecta 3 veces

    //Contrasenia por defecto
    //parameter correct_password = 16'b0011_0111_0110_0001;// contrasenia correcta 3761
    reg [2:0] state, next_state; //registros del estado actual y siguiente estado
    reg [1:0] intentos; // Contador para intentos fallidos
    reg [63:0] BALANCE;  //Cotador de balances
    reg [15:0] pin_tecleado;        // PIN tecleado por el usuario
    reg [1:0] digitos_ingresados;   // Número de dígitos ingresados

    //Transición de estados
    always @(posedge clk) begin
        if (rst) begin //Caso inicial y de reinicio, se establecen condiciones iniciales
            state <= IDLE; //Se establce como estado inicial IDLE
        end else begin
            state <= next_state; //Caso actual para a ser el siguiente estado
        end
    end
    
    //máquina de estados
    always @(*) begin
        next_state = state;//Siguiente estado es el estado actual
        case (state)
            IDLE: begin //Caso inicial maquina estados
                if (TARJETA_RECIBIDA) begin //Si detecto una tarjeta
                    next_state = ESPERA_TARJETA;//Espero contrasenia
                end
            end
    
            ESPERA_TARJETA: begin //Caso donde espero por una tarjeta
                next_state = LEER_PIN; //Verifico pin
            end

            LEER_PIN: begin
                if (DIGITO_STB) begin
                    if (digitos_ingresados == 3) begin
                        next_state = VERIFICAR_PIN;
                    end else begin
                        next_state = LEER_PIN;
                    end
                end else begin
                    next_state = LEER_PIN;
                end
                
            end
            
            VERIFICAR_PIN: begin //Caso donde verifico contrasenia
                if (PIN == pin_tecleado) begin //Contrsenia correcta
                    next_state = SELECCIONAR_TRANSACCION; //Verifico el tipo de transacion
                end else begin //Contrasenia incorrecta
                    next_state = WRONG_PIN;
                end
            end
            
            SELECCIONAR_TRANSACCION: begin //Caso donde verifico el tipo de transacion
                if (TIPO_TRANS == 0) begin //Realizo un deposito
                    next_state = PROCESAR_DEPOSITO; 
                end else if (TIPO_TRANS == 1) begin
                    next_state = PROCESAR_RETIRO;//Realizo un retiro
                end else begin
                    next_state = IDLE; //No realizo deposito ni retiro
                end
            end

            PROCESAR_DEPOSITO: begin
                next_state = JUMP_IDLE;
            end
            
            PROCESAR_RETIRO : begin
                next_state = JUMP_IDLE;
            end

            WRONG_PIN: begin //Caso de clave erronea
                if (intentos > 2) begin // Si el contador de intentos es mayor igual a  3
                    next_state = BLOCKED; //Activo alarma de bloqueo
                end else begin //Caso contrario pido que se ingrese contrasenia correcta
                    next_state = VERIFICAR_PIN;
                end
            end

            BLOCKED: begin
                //Permanezco bloqueado hasta reiniciar sistema
            end

            JUMP_IDLE:
             begin
                next_state = IDLE;
             end
            
        endcase
    end

    //Comportamiento salidas cajero_automatico, siempre que exista un cambio en el flanco positivo de la senial de reloj
    always @(posedge clk) begin
        if (rst) begin //Estado inicial seniales de salida
            BALANCE_ACTUALIZADO <= 0;
            ENTREGAR_DINERO <= 0;
            PIN_INCORRECTO <= 0;
            ADVERTENCIA <= 0;
            BLOQUEO <= 0;
            FONDOS_INSUFICIENTES <= 0;
            intentos <= 0;
            BALANCE <= 0;
            pin_tecleado <= 0;
            digitos_ingresados <= 0; 

        end else begin

            case (state)//Comportamiento de las salidas ante cambios de estados
                IDLE: begin //Caso inicial
                    BALANCE_ACTUALIZADO <= 0;
                    ENTREGAR_DINERO <= 0;
                    PIN_INCORRECTO <= 0;
                    ADVERTENCIA <= 0;
                    BLOQUEO <= 0;
                    FONDOS_INSUFICIENTES <= 0;
                    intentos <= 0;
                    BALANCE <= 0;
                    pin_tecleado <= 0;
                    digitos_ingresados <= 0; 
                end
                
                ESPERA_TARJETA: begin 
                    //Espero pin
                end


                LEER_PIN: begin
                    // Se almacena cada dígito del PIN tecleado
                    if (DIGITO_STB) begin
                        pin_tecleado <= {pin_tecleado[11:0], DIGITO};
                        digitos_ingresados <= digitos_ingresados + 1;
                    end
                end
                
                VERIFICAR_PIN: begin
                    //Cada vez que el usuario presiona un dígito,
                    //la señal DIGITO_STB se pone en 1 durante un ciclo de 
                    //reloj y se actualiza el valor de la entrada DIGITO.
                    //Una vez introducidos los 4 dígitos del número de PIN, el resultado se compara con
                    // el de la entrada PIN.
                end
                
                SELECCIONAR_TRANSACCION: begin 
                    //Verifico tipo de transacion
                end
                
                PROCESAR_DEPOSITO: begin
                    if (MONTO_STB) begin
                        BALANCE <= BALANCE_INICIAL + MONTO;
                        BALANCE_ACTUALIZADO <= 1;
                    end
                end

                PROCESAR_RETIRO: begin
                    if (MONTO_STB) begin
                        if (MONTO <= BALANCE_INICIAL) begin
                            BALANCE <= BALANCE_INICIAL - MONTO;
                            BALANCE_ACTUALIZADO <= 1;
                            ENTREGAR_DINERO <= 1;
                        end else begin
                            FONDOS_INSUFICIENTES <= 1;
                        end
                    end
                end

                WRONG_PIN:begin
                    PIN_INCORRECTO <= 1;
                    intentos <= intentos + 1;
                    if (intentos == 2) begin
                        ADVERTENCIA <= 1;
                    end else if (intentos > 2) begin
                        BLOQUEO <=1;
                    end
                end

                JUMP_IDLE: begin
                
                end
                
            endcase
        end
    end
endmodule

Tarea3/src/testebench.v
`include "cajeroAutomatico.v"
`include "tester.v"

module cajero_automatico_tb;
    // Seniales para conectar el tester con el DUT
    wire clk;
    wire rst;
    wire TARJETA_RECIBIDA;
    wire TIPO_TRANS;
    wire MONTO_STB;
    wire DIGITO_STB;
    wire [3:0] DIGITO;
    wire [15:0] PIN;
    wire [31:0] MONTO;
    wire [63:0] BALANCE_INICIAL;
    wire BALANCE_ACTUALIZADO;
    wire ENTREGAR_DINERO;
    wire PIN_INCORRECTO;
    wire ADVERTENCIA;
    wire BLOQUEO;
    wire FONDOS_INSUFICIENTES;

    // Archivo para guardar la simulación
    initial begin
        $dumpfile("resultados_cajero_automatico.vcd");
        $dumpvars(-1, U0);
    end

    // Instancia del módulo cajero_automatico (DUT)
    cajero_automatico U0 (
        .clk(clk),
        .rst(rst),
        .TARJETA_RECIBIDA(TARJETA_RECIBIDA),
        .TIPO_TRANS(TIPO_TRANS),
        .MONTO_STB(MONTO_STB),
        .DIGITO_STB(DIGITO_STB),
        .DIGITO(DIGITO),
        .PIN(PIN),
        .MONTO(MONTO),
        .BALANCE_INICIAL(BALANCE_INICIAL),
        .BALANCE_ACTUALIZADO(BALANCE_ACTUALIZADO),
        .ENTREGAR_DINERO(ENTREGAR_DINERO),
        .PIN_INCORRECTO(PIN_INCORRECTO),
        .ADVERTENCIA(ADVERTENCIA),
        .BLOQUEO(BLOQUEO),
        .FONDOS_INSUFICIENTES(FONDOS_INSUFICIENTES)
    );

    // Instancia del módulo tester
    tester T0 (
        .clk(clk),
        .rst(rst),
        .TARJETA_RECIBIDA(TARJETA_RECIBIDA),
        .TIPO_TRANS(TIPO_TRANS),
        .MONTO_STB(MONTO_STB),
        .DIGITO_STB(DIGITO_STB),
        .DIGITO(DIGITO),
        .PIN(PIN),
        .MONTO(MONTO),
        .BALANCE_INICIAL(BALANCE_INICIAL),
        .BALANCE_ACTUALIZADO(BALANCE_ACTUALIZADO),
        .ENTREGAR_DINERO(ENTREGAR_DINERO),
        .PIN_INCORRECTO(PIN_INCORRECTO),
        .ADVERTENCIA(ADVERTENCIA),
        .BLOQUEO(BLOQUEO),
        .FONDOS_INSUFICIENTES(FONDOS_INSUFICIENTES)
    );
endmodule

Tarea3/src/resultados_cajero_automatico.vcd
$date
	Tue Oct 01 13:02:43 2024
$end
$version
	Icarus Verilog
$end
$timescale
	1s
$end
$scope module cajero_automatico_tb $end
$scope module U0 $end
$var wire 64 ! BALANCE_INICIAL [63:0] $end
$var wire 4 " DIGITO [3:0] $end
$var wire 1 # DIGITO_STB $end
$var wire 32 $ MONTO [31:0] $end
$var wire 1 % MONTO_STB $end
$var wire 16 & PIN [15:0] $end
$var wire 1 ' TARJETA_RECIBIDA $end
$var wire 1 ( TIPO_TRANS $end
$var wire 1 ) clk $end
$var wire 1 * rst $end
$var reg 1 + ADVERTENCIA $end
$var reg 64 , BALANCE [63:0] $end
$var reg 1 - BALANCE_ACTUALIZADO $end
$var reg 1 . BLOQUEO $end
$var reg 1 / ENTREGAR_DINERO $end
$var reg 1 0 FONDOS_INSUFICIENTES $end
$var reg 1 1 PIN_INCORRECTO $end
$var reg 2 2 digitos_ingresados [1:0] $end
$var reg 2 3 intentos [1:0] $end
$var reg 3 4 next_state [2:0] $end
$var reg 16 5 pin_tecleado [15:0] $end
$var reg 3 6 state [2:0] $end
$upscope $end
$upscope $end
$enddefinitions $end
#0
$dumpvars
bx 6
bx 5
bx 4
bx 3
bx 2
x1
x0
x/
x.
x-
bx ,
x+
1*
0)
0(
0'
b11011101100001 &
0%
b0 $
0#
b0 "
b10011100010000 !
$end
#5
b0 4
b0 6
b0 2
b0 5
b0 ,
b0 3
00
0.
0+
01
0/
0-
1)
#10
0)
0*
#15
1)
#20
b1 4
0)
1'
#25
b10 4
b1 6
1)
#30
0)
#35
b10 6
1)
#40
0)
1#
b11 "
#45
b1 2
b11 5
1)
#50
0)
0#
#55
1)
#60
0)
#65
1)
#70
0)
1#
b111 "
#75
b10 2
b110111 5
1)
#80
0)
0#
#85
1)
#90
0)
#95
1)
#100
0)
1#
b110 "
#105
b11 4
b11 2
b1101110110 5
1)
#110
b10 4
0)
0#
#115
1)
#120
0)
#125
1)
#130
b11 4
0)
1#
b1 "
#135
b100 4
b0 2
b11011101100001 5
b11 6
1)
#140
b100 4
0)
0#
#145
b101 4
b100 6
1)
#150
0)
1%
b11111010000 $
#155
b111 4
b101 6
1)
#160
0)
#165
b0 4
b111 6
1-
b10111011100000 ,
1)
#170
0)
0%
#175
b1 4
b0 6
1)
#180
0)
#185
b10 4
b1 6
b0 5
b0 ,
0-
1)
#190
0)
#195
b10 6
1)
#200
0)
#205
1)
#210
0)
#215
1)
#220
0)
#225
1)
#230
0)
#235
1)
#240
0)
#245
1)
#250
0)
#255
1)
#260
0)
#265
1)
#270
0)
#275
1)
#280
0)
#285
1)
#290
0)
#295
1)
#300
0)
#305
1)
#310
0)
#315
1)
#320
0)
1*
#325
b1 4
b0 6
1)
#330
0)
0*
#335
b10 4
b1 6
1)
#340
0)
#345
b10 6
1)
#350
0)
#355
1)
#360
0)
#365
1)
#370
0)
1#
#375
b1 2
b1 5
1)
#380
0)
0#
#385
1)
#390
0)
#395
1)
#400
0)
1#
#405
b10 2
b10001 5
1)
#410
0)
0#
#415
1)
#420
0)
#425
1)
#430
0)
1#
#435
b11 4
b11 2
b100010001 5
1)
#440
b10 4
0)
0#
#445
1)
#450
0)
#455
1)
#460
b11 4
0)
1#
#465
b0 4
b11 6
b0 2
b1000100010001 5
1)
#470
b0 4
0)
0#
#475
b1 4
b0 6
1)
#480
0)
#485
b10 4
b1 6
b0 5
1)
#490
0)
#495
b10 6
1)
#500
0)
#505
1)
#510
0)
#515
1)
#520
0)
#525
1)
#530
0)
#535
1)
#540
0)
#545
1)
#550
0)
#555
1)
#560
0)
#565
1)
#570
0)
1#
b10 "
#575
b1 2
b10 5
1)
#580
0)
0#
#585
1)
#590
0)
#595
1)
#600
0)
1#
#605
b10 2
b100010 5
1)
#610
0)
0#
#615
1)
#620
0)
#625
1)
#630
0)
1#
#635
b11 4
b11 2
b1000100010 5
1)
#640
b10 4
0)
0#
