Tarea3/src/cmos_cells.v
module BUF(A, Y);
  input A;
  output Y;
  assign  Y = A;
endmodule

module NOT(A, Y);
  input A;
  output Y;
  assign  Y = ~A;
endmodule

module NAND(A, B, Y);
  input A, B;
  output Y;
  assign  Y = ~(A & B);
endmodule

module NOR(A, B, Y);
  input A, B;
  output Y;
  assign  Y = ~(A | B);
endmodule

module DFF(C, D, Q);
  input C, D; 
  output reg Q;
  always @(posedge C) #1 Q <= D;
endmodule

Tarea3/src/tester.v
module tester(
    output reg clk,
    output reg rst,
    output reg TARJETA_RECIBIDA,
    output reg TIPO_TRANS,
    output reg MONTO_STB,
    output reg DIGITO_STB,
    output reg [3:0] DIGITO,
    output reg [15:0] PIN,
    output reg [31:0] MONTO,
    output reg [63:0] BALANCE_INICIAL,
    input wire BALANCE_ACTUALIZADO,
    input wire ENTREGAR_DINERO,
    input wire PIN_INCORRECTO,
    input wire ADVERTENCIA,
    input wire BLOQUEO,
    input wire FONDOS_INSUFICIENTES
);

    // Generación de señal de reloj (clk)
    initial clk = 0;
    always #5 clk = ~clk; // Reloj de periodo 10 unidades de tiempo

    // Proceso de pruebas
    // Inicialización de señales
    initial begin
        // Reset inicial
        rst = 1;
        TARJETA_RECIBIDA = 0;
        TIPO_TRANS = 0;
        MONTO_STB = 0;
        DIGITO_STB = 0;
        DIGITO = 0;
        PIN = 16'b0011_0111_0110_0001; // PIN correcto: 3761
        MONTO = 0;
        BALANCE_INICIAL = 64'd10000; // Balance inicial: 10,000
        #10 rst = 0;

        //**************************************Caso #1********************************************************
        //Se ingresa un BALANCE_INICIAL de 10 000, se ingresa el pin 3761, se ingresan los digitos
        //3,7,6,1, se realiza un deposito MONTO = 2000, por lo que BALANCE = 12 000 y se espera poner en 1 las
        //senial BALANCE_ACTUALIZADO = 1.
        // Simulación de insertar tarjeta
        #10 TARJETA_RECIBIDA = 1;
        // Simulación de ingreso de PIN correcto
        #20 DIGITO = 4'd3; DIGITO_STB = 1;
        #10 DIGITO_STB = 0;
        #20 DIGITO = 4'd7; DIGITO_STB = 1;
        #10 DIGITO_STB = 0;
        #20 DIGITO = 4'd6; DIGITO_STB = 1;
        #10 DIGITO_STB = 0;
        #20 DIGITO = 4'd1; DIGITO_STB = 1;
        #10 DIGITO_STB = 0;
        // Espera para verificar el PIN
        #5;
        // Simulación de seleccionar deposito (TIPO_TRANS = 0) y monto
        #10 TIPO_TRANS = 0; MONTO = 32'd2000; MONTO_STB = 1; //Monto 2000
        #20 MONTO_STB = 0; //Se duplica el tiempo de esta senial
        // Espera para procesar el deposito
        #50;
        //**************************************Fin caso #1********************************************************

        //**************************************Caso #2********************************************************
        //Se ingresa un BALANCE_INICIAL de 10 000, se ingresa el pin 3761, se ingresan los digitos
        //3,7,6,1, se realiza un retiro MONTO = 2000, por lo que BALANCE = 8000 y se espera poner en 1 las
        //senial BALANCE_ACTUALIZADO = 1 y  ENTREGAR_DINERO = 1.
        // Simulación de insertar tarjeta
        #10 TARJETA_RECIBIDA = 1;
        // Simulación de ingreso de PIN correcto
        #20 DIGITO = 4'd3; DIGITO_STB = 1;
        #10 DIGITO_STB = 0;
        #20 DIGITO = 4'd7; DIGITO_STB = 1;
        #10 DIGITO_STB = 0;
        #20 DIGITO = 4'd6; DIGITO_STB = 1;
        #10 DIGITO_STB = 0;
        #20 DIGITO = 4'd1; DIGITO_STB = 1;
        #10 DIGITO_STB = 0;
        // Espera para verificar el PIN
        #5;
        // Simulación de seleccionar retiro (TIPO_TRANS = 1) y monto
        #10 TIPO_TRANS = 1; MONTO = 32'd2000; MONTO_STB = 1; //Monto 2000
        #20 MONTO_STB = 0; //Se duplica el tiempo de esta senial
        // Espera para procesar el retiro
        #50;
        //**************************************Fin caso #2********************************************************

        //**************************************Caso #3********************************************************
        //Se ingresa un BALANCE_INICIAL de 0, se ingresa el pin 3761, se ingresan los digitos
        //3,7,6,1, se realiza un retiro MONTO = 2000, por lo que FONDOS_INSUFICIENTES = 1.
        #10 BALANCE_INICIAL = 64'd00000; // Balance inicial: 10,000
        // Simulación de insertar tarjeta
        #10 TARJETA_RECIBIDA = 1;
        // Simulación de ingreso de PIN correcto
        #20 DIGITO = 4'd3; DIGITO_STB = 1;
        #10 DIGITO_STB = 0;
        #20 DIGITO = 4'd7; DIGITO_STB = 1;
        #10 DIGITO_STB = 0;
        #20 DIGITO = 4'd6; DIGITO_STB = 1;
        #10 DIGITO_STB = 0;
        #20 DIGITO = 4'd1; DIGITO_STB = 1;
        #10 DIGITO_STB = 0;
        // Espera para verificar el PIN
        #5;
        // Simulación de seleccionar retiro (TIPO_TRANS = 1) y monto
        #10 TIPO_TRANS = 1; MONTO = 32'd2000; MONTO_STB = 1; //Monto 2000
        #20 MONTO_STB = 0; //Se duplica el tiempo de esta senial
        // Espera para procesar el retiro
        #50;
        //**************************************Fin caso #3********************************************************

        //**************************************Caso #4********************************************************
        // Simulación de insertar un PIN incorrecto
        #100 rst = 1; #10 rst = 0; // Resetear para la siguiente prueba
        #20 TARJETA_RECIBIDA = 1;
        #20 DIGITO = 4'd1; DIGITO_STB = 1;
        #10 DIGITO_STB = 0;
        #20 DIGITO = 4'd1; DIGITO_STB = 1;
        #10 DIGITO_STB = 0;
        #20 DIGITO = 4'd1; DIGITO_STB = 1;
        #10 DIGITO_STB = 0;
        #20 DIGITO = 4'd1; DIGITO_STB = 1;
        #10 DIGITO_STB = 0;

        // Espera para verificar el PIN incorrecto
        #30;

        // Simulación de repetir PIN incorrecto dos veces más
        #50;
        #20 DIGITO = 4'd2; DIGITO_STB = 1;
        #10 DIGITO_STB = 0;
        #20 DIGITO = 4'd2; DIGITO_STB = 1;
        #10 DIGITO_STB = 0;
        #20 DIGITO = 4'd2; DIGITO_STB = 1;
        #10 DIGITO_STB = 0;
        #20 DIGITO = 4'd2; DIGITO_STB = 1;
        #10 DIGITO_STB = 0;
        // Verificar que el sistema se bloquee después del tercer intento
        #50;
        #20 DIGITO = 4'd3; DIGITO_STB = 1;
        #10 DIGITO_STB = 0;
        #20 DIGITO = 4'd3; DIGITO_STB = 1;
        #10 DIGITO_STB = 0;
        #20 DIGITO = 4'd3; DIGITO_STB = 1;
        #10 DIGITO_STB = 0;
        #20 DIGITO = 4'd3; DIGITO_STB = 1;
        #10 DIGITO_STB = 0;
        //**************************************Fin caso #4********************************************************
        #50 TIPO_TRANS = 0;
        #50 rst = 1;
        #10 rst = 0;

        // Fin de la simulación
        #500 $finish;
    end

endmodule

Tarea3/src/cajeroAutomatico.v
module cajero_automatico (
    //Entradas
    input wire clk, //Senial de reloj
    input wire rst, //Senial de reinicio
    input wire TARJETA_RECIBIDA, //Senial tarjeta recibida
    input wire TIPO_TRANS, //Senial tipo transacion 0 desposito 1 retiro
    input wire MONTO_STB, // Senial de entrada que se pone en 1 durante un solo ciclo de reloj (STB) cuando se ha actualizado el valor del MONTO a través del teclado
    input wire DIGITO_STB, //Senial de entrada que se pone en 1 durante un solo ciclo de reloj (STB) cuando se presiona un botón en el teclado. La lectura del PIN debe compararse con los valores de la entrada DIGITO cuando DIGITO_STB=1.
    input wire [3:0] DIGITO, // Ultimo dígito tecleado por el usuario
    input wire [15:0] PIN, //Entrada de 16 bits donde cada grupo de 4 bits representa un dígito del PIN de la tarjeta que se recibió
    input wire [31:0] MONTO, //Entrada de 32 bits que representa el monto de la transacción expresado en binario.
    input wire [63:0] BALANCE_INICIAL, //Entrada de 64 bits que contiene el balance de la cuenta al inicio de cada transacción. Debe tener su valor actualizado al momento en que se digita el pin correcto. Se debe garantizar que el banco de pruebas se ajuste a este comportamiento. 
    //Salidas
    output reg BALANCE_ACTUALIZADO, //Salida de un bit para indicar que una transacción fue exitosa y que se actualizó el balance en la cuenta, tanto para depósitos como para retiros
    output reg ENTREGAR_DINERO, // Salida de un bit para indicarle al cajero que entregue el MONTO durante una transacción de retiro
    output reg PIN_INCORRECTO, // Senial que indica que el valor del PIN recibido a través del teclado (la entrada DIGITO) es distinto del PIN de la tarjeta especificado en la entrada PIN.
    output reg ADVERTENCIA, // Salida binaria que se enciende cuando el usuario ha introducido el PIN de forma incorrecta dos veces 
    output reg BLOQUEO,//Salida binaria que se enciende cuando el usuario ha introducido el pin de forma incorrecta 3 veces
    output reg FONDOS_INSUFICIENTES // Senial salida cuando no hay suficientes fondos
);

    //Definicion de los estados del cajero automatico
    parameter IDLE = 4'b0000;                 // Estado inicial
    parameter ESPERA_TARJETA = 4'b0001;       // Espera de tarjeta
    parameter LEER_PIN = 4'b0010;             // Lectura de pin
    parameter VERIFICAR_PIN = 4'b0011;        // Verificacion del pin
    parameter SELECCIONAR_TRANSACCION = 4'b0100; // Seleccion de tipo de transaccion
    parameter PROCESAR_OPERACION = 4'b0101;//Procesamiento desposito o retiro
    parameter WRONG_PIN = 4'b0110;            // Pin incorrecto
    parameter BLOCKED = 4'b0111;              // Bloqueo del sistema

    //Contrasenia por defecto
    //parameter correct_password = 16'b0011_0111_0110_0001;// contrasenia correcta 3761
    reg [2:0] state, next_state; //registros del estado actual y siguiente estado
    reg [1:0] intentos; // Contador para intentos fallidos
    reg [63:0] BALANCE;  //Cotador de balances
    reg [15:0] pin_tecleado;        // PIN tecleado por el usuario
    reg [1:0] digitos_ingresados;   // Número de dígitos ingresados

    //Transición de estados
    always @(posedge clk) begin
        if (rst) begin //Caso inicial y de reinicio, se establecen condiciones iniciales
            state <= IDLE; //Se establce como estado inicial IDLE
        end else begin
            state <= next_state; //Caso actual para a ser el siguiente estado
        end
    end
    
    //máquina de estados
    always @(*) begin
        next_state = state;//Siguiente estado es el estado actual
        case (state)
            IDLE: begin //Caso inicial maquina estados
                if (TARJETA_RECIBIDA) begin //Si detecto una tarjeta
                    next_state = ESPERA_TARJETA;//Espero contrasenia
                end
            end
    
            ESPERA_TARJETA: begin //Caso donde espero por una tarjeta
                next_state = LEER_PIN; //Verifico pin
            end

            LEER_PIN: begin
                if (DIGITO_STB) begin
                    if (digitos_ingresados == 3) begin
                        next_state = VERIFICAR_PIN;
                    end else begin
                        next_state = LEER_PIN;
                    end
                end else begin
                    next_state = LEER_PIN;
                end
                
            end
            
            VERIFICAR_PIN: begin //Caso donde verifico contrasenia
                if (PIN == pin_tecleado) begin //Contrsenia correcta
                    next_state = SELECCIONAR_TRANSACCION; //Verifico el tipo de transacion
                end else begin //Contrasenia incorrecta
                    next_state = WRONG_PIN;
                end
            end
            
            SELECCIONAR_TRANSACCION: begin //Caso donde verifico el tipo de transacion
                next_state = PROCESAR_OPERACION;
            end

            PROCESAR_OPERACION: begin
                next_state = IDLE;
            end

            WRONG_PIN: begin //Caso de clave erronea
                if (intentos > 2) begin // Si el contador de intentos es mayor igual a  3
                    next_state = BLOCKED; //Activo alarma de bloqueo
                end else begin //Caso contrario pido que se ingrese contrasenia correcta
                    next_state = LEER_PIN;
                end
            end

            BLOCKED: begin
                //Permanezco bloqueado hasta reiniciar sistema
            end
            
        endcase
    end

    //Comportamiento salidas cajero_automatico, siempre que exista un cambio en el flanco positivo de la senial de reloj
    always @(posedge clk) begin
        if (rst) begin //Estado inicial seniales de salida
            BALANCE_ACTUALIZADO <= 0;
            ENTREGAR_DINERO <= 0;
            PIN_INCORRECTO <= 0;
            ADVERTENCIA <= 0;
            BLOQUEO <= 0;
            FONDOS_INSUFICIENTES <= 0;
            intentos <= 0;
            BALANCE <= 0;
            pin_tecleado <= 0;
            digitos_ingresados <= 0; 

        end else begin

            case (state)//Comportamiento de las salidas ante cambios de estados
                IDLE: begin //Caso inicial
                    BALANCE_ACTUALIZADO <= 0;
                    ENTREGAR_DINERO <= 0;
                    PIN_INCORRECTO <= 0;
                    ADVERTENCIA <= 0;
                    BLOQUEO <= 0;
                    FONDOS_INSUFICIENTES <= 0;
                    intentos <= 0;
                    BALANCE <= 0;
                    pin_tecleado <= 0;
                    digitos_ingresados <= 0; 
                end
                
                ESPERA_TARJETA: begin 
                    //Espero pin
                end


                LEER_PIN: begin
                    // Se almacena cada dígito del PIN tecleado
                    if (DIGITO_STB) begin
                        pin_tecleado <= {pin_tecleado[11:0], DIGITO};
                        digitos_ingresados <= digitos_ingresados + 1;
                    end
                end
                
                VERIFICAR_PIN: begin
                    //Verifico pin
                end
                
                SELECCIONAR_TRANSACCION: begin 
                    //Verifico tipo de transacion
                end

                PROCESAR_OPERACION: begin

                    if (MONTO_STB && TIPO_TRANS == 1'b0) begin
                        BALANCE <= BALANCE_INICIAL + MONTO;
                        BALANCE_ACTUALIZADO <= 1;

                    end if (MONTO_STB && TIPO_TRANS == 1'b1) begin

                        if (MONTO <= BALANCE_INICIAL) begin
                            BALANCE <= BALANCE_INICIAL - MONTO;
                            BALANCE_ACTUALIZADO <= 1;
                            ENTREGAR_DINERO <= 1;

                        end else begin
                            FONDOS_INSUFICIENTES <= 1;
                        end
                    end
                end
                
                WRONG_PIN:begin
                    PIN_INCORRECTO <= 1;
                    intentos <= intentos + 1;
                    if (intentos == 2) begin
                        ADVERTENCIA <= 1;
                    end else if (intentos > 2) begin
                        BLOQUEO <=1;
                    end
                end
                
            endcase
        end
    end
endmodule

Tarea3/src/testebench.v
`include "cmos_cells.v"
`include "cajeroAutomatico.v"
`include "tester.v"

module cajero_automatico_tb;
    // Seniales para conectar el tester con el DUT
    wire clk;
    wire rst;
    wire TARJETA_RECIBIDA;
    wire TIPO_TRANS;
    wire MONTO_STB;
    wire DIGITO_STB;
    wire [3:0] DIGITO;
    wire [15:0] PIN;
    wire [31:0] MONTO;
    wire [63:0] BALANCE_INICIAL;
    wire BALANCE_ACTUALIZADO;
    wire ENTREGAR_DINERO;
    wire PIN_INCORRECTO;
    wire ADVERTENCIA;
    wire BLOQUEO;
    wire FONDOS_INSUFICIENTES;

    // Archivo para guardar la simulación
    initial begin
        $dumpfile("resultados_cajero_automatico.vcd");
        $dumpvars(-1, U0);
    end

    // Instancia del módulo cajero_automatico (DUT)
    cajero_automatico U0 (
        .clk(clk),
        .rst(rst),
        .TARJETA_RECIBIDA(TARJETA_RECIBIDA),
        .TIPO_TRANS(TIPO_TRANS),
        .MONTO_STB(MONTO_STB),
        .DIGITO_STB(DIGITO_STB),
        .DIGITO(DIGITO),
        .PIN(PIN),
        .MONTO(MONTO),
        .BALANCE_INICIAL(BALANCE_INICIAL),
        .BALANCE_ACTUALIZADO(BALANCE_ACTUALIZADO),
        .ENTREGAR_DINERO(ENTREGAR_DINERO),
        .PIN_INCORRECTO(PIN_INCORRECTO),
        .ADVERTENCIA(ADVERTENCIA),
        .BLOQUEO(BLOQUEO),
        .FONDOS_INSUFICIENTES(FONDOS_INSUFICIENTES)
    );

    // Instancia del módulo tester
    tester T0 (
        .clk(clk),
        .rst(rst),
        .TARJETA_RECIBIDA(TARJETA_RECIBIDA),
        .TIPO_TRANS(TIPO_TRANS),
        .MONTO_STB(MONTO_STB),
        .DIGITO_STB(DIGITO_STB),
        .DIGITO(DIGITO),
        .PIN(PIN),
        .MONTO(MONTO),
        .BALANCE_INICIAL(BALANCE_INICIAL),
        .BALANCE_ACTUALIZADO(BALANCE_ACTUALIZADO),
        .ENTREGAR_DINERO(ENTREGAR_DINERO),
        .PIN_INCORRECTO(PIN_INCORRECTO),
        .ADVERTENCIA(ADVERTENCIA),
        .BLOQUEO(BLOQUEO),
        .FONDOS_INSUFICIENTES(FONDOS_INSUFICIENTES)
    );
endmodule

Tarea3/src/resultados_cajero_automatico.vcd
$date
	Wed Oct 02 14:09:24 2024
$end
$version
	Icarus Verilog
$end
$timescale
	1s
$end
$scope module cajero_automatico_tb $end
$scope module U0 $end
$var wire 64 ! BALANCE_INICIAL [63:0] $end
$var wire 4 " DIGITO [3:0] $end
$var wire 1 # DIGITO_STB $end
$var wire 32 $ MONTO [31:0] $end
$var wire 1 % MONTO_STB $end
$var wire 16 & PIN [15:0] $end
$var wire 1 ' TARJETA_RECIBIDA $end
$var wire 1 ( TIPO_TRANS $end
$var wire 1 ) clk $end
$var wire 1 * rst $end
$var reg 1 + ADVERTENCIA $end
$var reg 64 , BALANCE [63:0] $end
$var reg 1 - BALANCE_ACTUALIZADO $end
$var reg 1 . BLOQUEO $end
$var reg 1 / ENTREGAR_DINERO $end
$var reg 1 0 FONDOS_INSUFICIENTES $end
$var reg 1 1 PIN_INCORRECTO $end
$var reg 2 2 digitos_ingresados [1:0] $end
$var reg 2 3 intentos [1:0] $end
$var reg 3 4 next_state [2:0] $end
$var reg 16 5 pin_tecleado [15:0] $end
$var reg 3 6 state [2:0] $end
$upscope $end
$upscope $end
$enddefinitions $end
#0
$dumpvars
bx 6
bx 5
bx 4
bx 3
bx 2
x1
x0
x/
x.
x-
bx ,
x+
1*
0)
0(
0'
b11011101100001 &
0%
b0 $
0#
b0 "
b10011100010000 !
$end
#5
b0 4
b0 6
b0 2
b0 5
b0 ,
b0 3
00
0.
0+
01
0/
0-
1)
#10
0)
0*
#15
1)
#20
b1 4
0)
1'
#25
b10 4
b1 6
1)
#30
0)
#35
b10 6
1)
#40
0)
1#
b11 "
#45
b1 2
b11 5
1)
#50
0)
0#
#55
1)
#60
0)
#65
1)
#70
0)
1#
b111 "
#75
b10 2
b110111 5
1)
#80
0)
0#
#85
1)
#90
0)
#95
1)
#100
0)
1#
b110 "
#105
b11 4
b11 2
b1101110110 5
1)
#110
b10 4
0)
0#
#115
1)
#120
0)
#125
1)
#130
b11 4
0)
1#
b1 "
#135
b100 4
b0 2
b11011101100001 5
b11 6
1)
#140
b100 4
0)
0#
#145
b101 4
b100 6
1)
#150
0)
#155
b0 4
b101 6
1)
1%
b11111010000 $
#160
0)
#165
b1 4
b0 6
1-
b10111011100000 ,
1)
#170
0)
#175
b10 4
b0 5
b0 ,
0-
b1 6
1)
0%
#180
0)
#185
b10 6
1)
#190
0)
#195
1)
#200
0)
#205
1)
#210
0)
#215
1)
#220
0)
#225
1)
#230
0)
#235
1)
#240
0)
#245
1)
#250
0)
#255
b1 2
b11 5
1)
1#
b11 "
#260
0)
#265
1)
0#
#270
0)
#275
1)
#280
0)
#285
b10 2
b110111 5
1)
1#
b111 "
#290
0)
#295
1)
0#
#300
0)
#305
1)
#310
0)
#315
b11 4
b11 2
b1101110110 5
1)
1#
b110 "
#320
0)
#325
b10 4
1)
0#
#330
0)
#335
1)
#340
0)
#345
b11 6
b0 2
b11011101100001 5
b100 4
1)
1#
b1 "
#350
0)
#355
b100 6
b101 4
1)
0#
#360
0)
#365
b0 4
b101 6
1)
#370
0)
1%
1(
#375
b1 4
1/
1-
b1111101000000 ,
b0 6
1)
#380
0)
#385
b10 4
b1 6
b0 5
b0 ,
0/
0-
1)
#390
0)
0%
#395
b10 6
1)
#400
0)
#405
1)
#410
0)
#415
1)
#420
0)
#425
1)
#430
0)
#435
1)
#440
0)
#445
1)
#450
0)
b0 !
#455
1)
#460
0)
#465
1)
#470
0)
#475
1)
#480
0)
1#
b11 "
#485
b1 2
b11 5
1)
#490
0)
0#
#495
1)
#500
0)
#505
1)
#510
0)
1#
b111 "
#515
b10 2
b110111 5
1)
#520
0)
0#
#525
1)
#530
0)
#535
1)
#540
0)
1#
b110 "
#545
b11 4
b11 2
b1101110110 5
1)
#550
b10 4
0)
0#
#555
1)
#560
0)
#565
1)
#570
b11 4
0)
1#
b1 "
#575
b100 4
b0 2
b11011101100001 5
b11 6
1)
#580
b100 4
0)
0#
#585
b101 4
b100 6
1)
#590
0)
#595
b0 4
b101 6
1)
1%
#600
0)
#605
b1 4
b0 6
10
1)
#610
0)
#615
b10 4
b0 5
00
b1 6
1)
0%
#620
0)
#625
b10 6
1)
#630
0)
#635
1)
#640
0)
#645
1)
#650
0)
#655
1)
#660
0)
#665
1)
#670
0)
#675
1)
#680
0)
#685
1)
#690
0)
#695
1)
#700
0)
#705
1)
#710
0)
#715
1)
#720
0)
#725
1)
#730
0)
#735
1)
#740
0)
#745
1)
#750
0)
#755
1)
#760
0)
#765
b1 4
b0 6
1)
1*
#770
0)
#775
b10 4
b1 6
1)
0*
#780
0)
#785
b10 6
1)
#790
0)
#795
1)
#800
0)
#805
1)
#810
0)
#815
b1 2
b1 5
1)
1#
#820
0)
#825
1)
0#
#830
0)
#835
1)
#840
0)
#845
b10 2
b10001 5
1)
1#
#850
0)
#855
1)
0#
#860
0)
#865
1)
#870
0)
#875
b11 4
b11 2
b100010001 5
1)
1#
#880
0)
#885
b10 4
1)
0#
#890
0)
#895
1)
#900
0)
#905
b11 6
b0 2
b1000100010001 5
b110 4
1)
1#
#910
0)
#915
b110 6
b10 4
1)
0#
#920
0)
#925
b10 6
b1 3
11
1)
#930
0)
#935
1)
#940
0)
#945
1)
#950
0)
#955
1)
#960
0)
#965
1)
#970
0)
#975
1)
#980
0)
#985
1)
#990
0)
#995
1)
#1000
0)
#1005
1)
#1010
0)
#1015
b1 2
b1000100010010 5
1)
1#
b10 "
#1020
0)
#1025
1)
0#
#1030
0)
#1035
1)
#1040
0)
#1045
b10 2
b1000100100010 5
1)
1#
#1050
0)
#1055
1)
0#
#1060
0)
#1065
1)
#1070
0)
#1075
b11 4
b11 2
b1001000100010 5
1)
1#
#1080
0)
#1085
b10 4
1)
0#
#1090
0)
#1095
1)
#1100
0)
#1105
b11 6
b0 2
b10001000100010 5
b110 4
1)
1#
#1110
0)
#1115
b110 6
b10 4
1)
0#
#1120
0)
#1125
b10 6
b10 3
1)
#1130
0)
#1135
1)
#1140
0)
#1145
1)
#1150
0)
#1155
1)
#1160
0)
#1165
1)
#1170
0)
#1175
1)
#1180
0)
#1185
b1 2
b10001000100011 5
1)
1#
b11 "
#1190
0)
#1195
1)
0#
#1200
0)
#1205
1)
#1210
0)
#1215
b10 2
b10001000110011 5
1)
1#
#1220
0)
#1225
1)
0#
#1230
0)
#1235
1)
#1240
0)
#1245
b11 4
b11 2
b10001100110011 5
1)
1#
#1250
0)
#1255
b10 4
1)
0#
#1260
0)
#1265
1)
#1270
0)
#1275
b0 2
b11001100110011 5
b11 6
b110 4
1)
1#
#1280
0)
#1285
b110 6
b10 4
1)
0#
#1290
0)
#1295
1+
b11 3
b10 6
1)
#1300
0)
#1305
1)
#1310
0)
#1315
1)
#1320
0)
#1325
1)
#1330
0)
#1335
1)
0(
#1340
0)
#1345
1)
#1350
0)
#1355
1)
#1360
0)
#1365
1)
#1370
0)
#1375
1)
#1380
0)
#1385
b1 4
b0 6
b0 5
b0 3
0+
01
1)
1*
#1390
0)
#1395
b10 4
b1 6
1)
0*
#1400
0)
#1405
b10 6
1)
