Tarea4/src/tester.v
module tester_generador (
    output reg clk,
    output reg rst,
    output reg START_STB,
    output reg RNW,
    output reg [6:0] I2C_ADDR,
    output reg SDA_IN,
    output reg [15:0] WR_DATA,
    input wire SDA_OE,
    input wire SCL,
    input wire SDA_OUT,
    input wire [15:0] RD_DATA
);

    // Generación de la señal de reloj (clk) con un período de 20 unidades de tiempo
    always begin
        #10 clk = ~clk;
    end

    initial begin
        // Inicializar señales
        clk = 0;
        rst = 1;
        START_STB = 0;
        RNW = 0;
        //SDA_IN = 1;
        I2C_ADDR = 7'b0111101; // Dirección I2C
        WR_DATA = 16'h1234;

        // Esperar para desactivar el reset
        #25 rst = 0;

        // Simular una transacción de escritura
        #50 START_STB = 1; RNW = 0; // Iniciar escritura
        // Enviar cada bit de I2C_ADDR a SDA_IN
        #50 START_STB = 0; // Finalizar la señal START_STB
        
        // Simular una transacción de lectura
        //#100 START_STB = 1; RNW = 1; // Iniciar lectura
        // Enviar cada bit de I2C_ADDR a SDA_IN de nuevo (si es necesario)
        //#50 START_STB = 0; // Finalizar la señal START_STB
        
        //#25 rst = 1; // Reiniciar para finalizar

        // Terminar la simulación
        #1000 $finish;
    end
endmodule

Tarea4/src/receptor.v
module  receptor_transacciones (
    //Entradas
    input wire clk_receptor, // Senial de reloj
    input wire rst_receptor, // Senial de reinicio, activa en 1
    input wire [6:0] I2C_ADDR_receptor,//Esta entrada proviene de un registro del CPU y contiene la dirección del receptor de transacciones. Cuando el receptor recibe una transacción, debe cerciorarse de que es una transacción para sí mismo, comparando el valor recibido en SDA_IN con el valor almacenado en este registro.
    input wire SCL,//Entrada de reloj para el I2C. El flanco activo de la señal SCL es el flanco creciente. Observe que SCL es una entrada del receptor, que deberá provenir del generador de transacciones o de un probador que emule su comportamiento.
    input wire SDA_OUT,//Entrada serial. Note que la dirección de esta señal es inversa a la del generador de transacciones. Debe tener el comportamiento especificado por el protocolo I2C para las condiciones de START, STOP y transacciones de escritura y lectura.
    input wire SDA_OE, //Habilitación de SDA_OUT. Entrada serial. Note que la dirección de esta señal es inversa a la del generador de transacciones. Se debe poner en 1 para aquellas porciones de la transacción donde el generador tiene control del bus I2C y ponerse en 0 para las porciones de la transacción donde el receptor tiene control del bus, de acuerdo con las especificaciones del protocolo.
    input wire [15:0] RD_DATA_receptor,//Note que la dirección de esta señal es inversa a la del generador de transacciones. Esta entrada debe producir los 16 bits que se envían desde el receptor de transacciones I2C durante una transacción de lectura recibida en SDA_OUT. Los bits de RD_DATA_receptor se deben enviar a través de SDA_IN de acuerdo con el protocolo.
    //Salidas
    output reg SDA_IN,//Salida serial enviada desde el receptor hacia el generador de transacciones. Debe tener el comportamiento especificado por el protocolo I2C para producir la indicación de ACK, así como proporcionar los datos de entrada en transacciones de lectura.
    output reg [15:0] WR_DATA_receptor //Salida paralela. Note que la dirección de esta señal es inversa a la del generador de transacciones. Contiene los 16 bits que se reciben por la interfaz I2C durante una transacción de escritura de acuerdo a este enunciado
    
);

    //Definicion de los estados del cajero automatico
    parameter IDLE = 0; 
    parameter INICIO = 1;                 //Estado inicial
    parameter LECTURA = 2;       // Espera de tarjeta
    parameter ESCRITURA = 3;             // Lectura de pin
    parameter PARADA = 4;        // Verificacion del pin

    //Variales internas
    reg [2:0] state_receptor, next_state_receptor; //registros del estado actual y siguiente estado
    reg [4:0] contador_bits_receptor;
    reg [4:0] contador_adr_receptor;
    reg ultimo_bit_adr;
    reg flag_comunicacion_receptor;
    reg [6:0] get_I2C_ADDR;

    //Transición de estados
    always @(posedge clk_receptor) begin
        if (rst_receptor) begin //Caso inicial y de reinicio, se establecen condiciones iniciales
            state_receptor <= IDLE; //Se establce como estado inicial IDLE
            SDA_IN <= 1;
            flag_comunicacion_receptor <=1;
        end else begin
            state_receptor <= next_state_receptor; //Caso actual para a ser el siguiente estado
        end
    end
    
    // Máquina de estados
    always @(*) begin
        next_state_receptor = state_receptor; // Siguiente estado es el estado actual
        case (state_receptor)

            IDLE: begin // Caso inicial maquina estados
            if (SCL && ~SDA_OUT) begin
                next_state_receptor = INICIO;
            end
            end

            INICIO: begin // Caso inicial maquina estados
                if (contador_adr_receptor == 8) begin
                    if (ultimo_bit_adr == 0) begin // Si RNW es 1, es una transacción de lectura
                        next_state_receptor = LECTURA;
                    end else if(ultimo_bit_adr == 1) begin // Si RNW es 0, es una transacción de escritura
                        next_state_receptor = ESCRITURA;
                    end
                end
            end
    
            LECTURA: begin //Aqui se envian tramas de 16 bits
                if (contador_bits_receptor < 15) begin
                    flag_comunicacion_receptor = 1; // Mientras haya bits que leer, la comunicación sigue
                end else if (SCL &&  SDA_IN) begin // Una vez que se ha leído todo, termina la comunicación
                    flag_comunicacion_receptor = 0;
                    next_state_receptor = PARADA;
                end
            end

            ESCRITURA: begin
                if (contador_bits_receptor < 15 ) begin // Mientras haya bits que escribir, la comunicación sigue
                    flag_comunicacion_receptor = 1;
                end else if (SCL &&  SDA_IN) begin  // Una vez que se ha escrito todo, termina la comunicación
                    flag_comunicacion_receptor = 0;
                    next_state_receptor = PARADA;
                end
            end

            PARADA:begin
                
                next_state_receptor = IDLE;

            end
           
            
        endcase
    end

        // Máquina de estados
    always @(posedge clk_receptor) begin
        if (rst_receptor) begin
            state_receptor <= IDLE; //Se establce como estado inicial IDLE
            SDA_IN <= 1;
            flag_comunicacion_receptor <=1;
        end else begin
            case (state_receptor)

                IDLE: begin // Caso inicial maquina estados
                    SDA_IN <= 0;
                end

                INICIO: begin // Caso inicial maquina estados
                   
                end
        
                LECTURA: begin //Aqui se envian tramas de 16 bits
                
                end

                ESCRITURA: begin
                
                end

                PARADA:begin
                    SDA_IN <= 1;
                end
                
            endcase
        end
    end


    always @(posedge SCL) begin
        if (rst_receptor) begin
            contador_bits_receptor <= 0;
            contador_adr_receptor <= 0;
            get_I2C_ADDR <= 7'b0; // Inicializar la variable
            ultimo_bit_adr <= 0;
        end else begin
            case (state_receptor) // Comportamiento de las salidas ante cambios de estados

                IDLE: begin // Caso inicial maquina estados
                    SDA_IN <= 0;
                end

                INICIO: begin // Caso inicial
                    if (contador_adr_receptor <= 6 ) begin
                        // Desplaza los bits de SDA_OUT hacia la derecha e inserta el nuevo bit en get_I2C_ADDR
                        get_I2C_ADDR <= {get_I2C_ADDR[5:0], SDA_OUT};
                        SDA_IN <= SDA_OUT;
                    end
                    if (contador_adr_receptor == 7 ) begin
                        ultimo_bit_adr <= SDA_OUT;
                        SDA_IN <= SDA_OUT;
                    end
                    if (contador_adr_receptor == 8 ) begin
                        SDA_IN <=1; //Envio un ACK
                    end
                    contador_adr_receptor <= contador_adr_receptor + 1; // Incrementar el contador de bits
                end

            
                LECTURA: begin
                    if (contador_bits_receptor <= 15) begin
                        // Desplaza los bits de RD_DATA a la izquierda e inserta el nuevo bit desde SDA_IN
                        SDA_IN <= {RD_DATA_receptor[14:0], SDA_OUT};
                        
                    end
                    contador_bits_receptor <= contador_bits_receptor + 1; // Incrementar el contador de bits
                    
                end

                ESCRITURA: begin
                    // Durante la escritura, envía los bits de WR_DATA por SDA_OUT uno a uno
                    if (contador_bits_receptor <= 15) begin
                        SDA_IN <= WR_DATA_receptor[15 - contador_bits_receptor]; // Enviar el bit correspondiente de WR_DATA
                        
                    end
                    contador_bits_receptor <= contador_bits_receptor + 1; // Incrementar el contador de bits
                end

                PARADA: begin
                    // Lógica para manejar el estado de PARADA
                    
                end
            endcase
        end
end

endmodule

Tarea4/src/generador.v
module generador_transacciones (
    //Entradas
    input wire clk, // Senial de reloj
    input wire rst, // Senial de reinicio, activo en bajo
    input wire START_STB,//Strobe (pulso de un ciclo de reloj). Indica al generador que el CPU quiere iniciar una transacción de I2C
    input wire RNW,//Esta señal indica la dirección de la transacción que deseaejecutar el CPU. Cuando RNW=1 se trata de una transacción de lectura y cuando RNW=0 se trata de una escritura.
    input wire [6:0] I2C_ADDR, //– Esta entrada proviene de un registro del CPU y contiene la dirección del receptor de transacciones con quien el generador se quiere comunicar.
    input wire SDA_IN, //Entrada serie proveniente del probador. Debe tener el comportamiento especificado por el protocolo I2C para producir la indicación de ACK, así como proporcionar los datos de entrada en transacciones de lectura
    input wire [15:0] WR_DATA,//– Entrada paralela. Contiene los 16 bits que se deben enviar por la interfaz I2C durante una transacción de escritura de acuerdo a este enunciado.
    //Salidas
    output reg SDA_OE, //Habilitación de SDA_OUT. Se debe poner en 1 para aquellas porciones de la transacción donde el generador tiene control del bus I2C y ponerse en 0 para las porciones de la transacción donde el receptor tiene control del bus, de acuerdo con las especificaciones del protocolo.
    output wire SCL, //Salida de reloj para el I2C. El flanco activo de la señal SCL es el flanco creciente. Observe que SCL es una salida del generador, que deberá tener una frecuencia del 25% de la frecuencia de la entrada CLK. El generador debe generar SCL con la frecuencia correcta para cualquier posible valor de la frecuencia de entrada CLK.
    output reg SDA_OUT, //Salida serial. Debe tener el comportamiento especificado por el protocolo I2C para las condiciones de INICIO, STOP y transacciones de escritura y lectura.
    output reg[15:0] RD_DATA//Esta salida debe producir los 16 bits que se reciben desde el receptor de transacciones I2C durante una transacción de lectura recibida en SDA_IN. Una vez que se ha recibido los 16 bits completos, el generador de transacciones debe enviar la condición de STOP de acuerdo al protocolo I2C.
);

    //Definicion de los estados del cajero automatico
    parameter INICIO = 0;  // Aqui se produce un condicion de inicio, se debe bajar SDA mientras el SCL permanece en alto (transacion no ocurre en un flanco del SCL)
    parameter ENVIAR_DIR_RECEPTOR = 1;
    parameter ESCRITURA = 2; // Escritura
    parameter LECTURA = 3; // Lectura
    parameter PARADA = 4;   //Indicacion de parar 

    //Variables intermedias
    reg [2:0] state, next_state; //registros del estado actual y siguiente estado
    reg [4:0] contador_bits; //Contador de bits para proceso de lectura o escritura
    reg [4:0] contador_adr;//Contador de bits de la direcion del recpetor
    reg flag_comunicacion;//Bandera que indica si se mantiene o no la comunicacion
    reg condicion_scl;//Selector de conmutacion reloj o señal permanece unicamente en alto

    //Fip flops
    always @(posedge clk) begin
        if (rst) begin //Caso inicial y de reinicio, se establecen condiciones iniciales
            state <= INICIO; //Se establce como estado inicial INICIO
            flag_comunicacion <= 0; //No existe comunicacion
            condicion_scl <= 0; //Reloj permanece en alto inicialmente
        end else begin
            state <= next_state; //Caso actual para a ser el siguiente estado
        end
    end
    
    //Logica combinacional
    always @(*) begin
        next_state = state; // Siguiente estado es el estado actual
        case (state)
            INICIO: begin // Caso inicial maquina estados
                //if (START_STB && SCL &&  ~SDA_IN) begin //Se inicia comunicacion el generador de transacciones debe producir la  condición de inicio. Es decir, debe bajar la señal SDA mientras el SCL permanece en alto.  Note que esta transición NO ocurre en un flanco del SCL.
                if (START_STB && SCL) begin //Se inicia comunicacion el generador de transacciones debe producir la  condición de inicio. Es decir, debe bajar la señal SDA mientras el SCL permanece en alto.  Note que esta transición NO ocurre en un flanco del SCL.
                    condicion_scl = 1;//Reloj conmuta
                    next_state = ENVIAR_DIR_RECEPTOR;//Envio direcion del receptor en cada flanco positivo de SCL
                end
                
            end

            /*
    
            ENVIAR_DIR_RECEPTOR:begin //Aqui envio 8 bits 7 primeros tienen direcion del recptor y ultimo bit indica si es escritura o lectura
                
                if (SDA_IN && START_STB && RNW && contador_adr > 7) begin //SDA en 1 recibo ACK del receptor, indica que se recibieron 8 bits
                    
                    next_state = LECTURA;
                end

                if (SDA_IN && START_STB && ~RNW && contador_adr > 7) begin //SDA en 1 recibo ACK del receptor, indica que se recibieron 8 bits
                    
                    next_state = ESCRITURA;
                end
                
            end
            */

            ENVIAR_DIR_RECEPTOR: begin
                if (contador_adr > 7) begin // Si contador_adr es mayor a 7
                    if (RNW) begin // Si RNW es 1, es una transacción de lectura
                        next_state = LECTURA;
                    end else begin // Si RNW es 0, es una transacción de escritura
                        next_state = ESCRITURA;
                    end
                end
            end
            
            LECTURA: begin // Aqui se envian tramas de 16 bits
                if (contador_bits < 15 && SDA_IN) begin
                    flag_comunicacion = 1; // Mientras haya bits que leer, la comunicación sigue
                end else begin // Una vez que se ha leído todo, termina la comunicación
                    flag_comunicacion = 0; // Se termino comunicacion
                    next_state = PARADA; //Proximo estado es el de PARADA
                end
            end

            ESCRITURA: begin
                if (contador_bits < 15  && SDA_IN) begin // Mientras haya bits que escribir, la comunicación sigue
                    flag_comunicacion = 1; // Continua la comunicacion
                end else begin  // Una vez que se ha escrito todo, termina la comunicación
                    flag_comunicacion = 0; // Termina la comunicacion
                    next_state = PARADA; //Proximi estado es PARADA
                end
            end

            PARADA:begin
                if (SCL &&  SDA_IN) begin //Una vez que se completa toda la transacción, el generador de transacciones debe enviar una condición de parada (P), que consiste en poner en alto la señal de SDA mientras el SCL también se encuentra en alto
                    flag_comunicacion = 0; // Se termina la comunicacion
                    condicion_scl = 0; //Reloj permanece en alto
                    next_state = INICIO; //Porximo estado INICIO
                end
            end
            
        endcase
    end

    //Generación del reloj de salida SCL  
    // La señal SCL es el reloj utilizado en el bus I2C, y este bloque de código se encarga de generar esa señal.
    // `clk_div2` es un registro que divide la frecuencia del reloj de entrada `clk` a la mitad.
    // `count_clock` es un contador de 2 bits que se incrementa con cada flanco positivo de `clk` y se utiliza para generar `clk_div4`.
    
    reg clk_div2; // Registro que divide la frecuencia del reloj a la mitad.
    wire clk_div4; // Señal que divide la frecuencia del reloj por cuatro.
    reg [1:0] count_clock; // Contador de 2 bits para llevar un seguimiento del ciclo del reloj.

    always @(posedge clk) begin
    if (rst) begin
        contador_bits <= 0; // Contador bits en 0
        contador_adr <= 0; // Contador bits de la direcion del receptor en 0
        clk_div2    <= 0; // Cuando rst está activo, se reinicia clk_div2 y el contador a 0.
        count_clock <= 0; // Contador del divisor de frecuencia en cero
    end else begin
        clk_div2    <= ~clk_div2; // Invertir clk_div2 en cada flanco positivo del reloj para dividir su frecuencia.
        count_clock <= count_clock+1; // Incrementar el contador de reloj.

        case (state)
            INICIO: begin // Caso inicial maquina estados
                SDA_OUT <= 0;
            end

            ENVIAR_DIR_RECEPTOR: begin
        
            end
            
            LECTURA: begin // Aqui se envian tramas de 16 bits
                
            end

            ESCRITURA: begin 
            end

            PARADA:begin
                SDA_OUT <= 1;
            end
            
        endcase

        end
    end

    assign clk_div4 = count_clock[1]; // La señal `clk_div4` se genera tomando el segundo bit del contador, dividiendo así la frecuencia del reloj por 4.
    assign SCL = condicion_scl ? count_clock[1] : 1'b1; // Seleciono si reloj conmuta o permanece en alto.
    // Incremento de cuenta_bits
    // Este bloque de código se activa en cada flanco positivo de SCL, la señal de reloj del bus I2C.
    // El código inicializa o reinicia ciertos registros cuando `rst` o `start_stb` están activos,
    // y en caso contrario, actualiza los registros relacionados con el contador de bits (cuenta_bits) y las señales SDA_OE y SDA_OUT.
   always @(posedge SCL) begin
    if (rst || START_STB) begin
        contador_bits <= 0;
        contador_adr <= 0;
    end else begin
        case (state) // Comportamiento de las salidas ante cambios de estados
            INICIO: begin // Caso inicial
                
            end

            ENVIAR_DIR_RECEPTOR: begin // Envio de datos
                if (contador_adr <= 6) begin // Si contador es menor o igual a 6 bits
                    SDA_OUT <= I2C_ADDR[6 - contador_adr]; // SDA out transmite contenido de WR_DATA
                end
                if (contador_adr == 7 && RNW) begin // Si deseo LEER ultimo bit es 1
                    SDA_OUT <= 1'b1; // Enviar 1 si RW LECTURA
                end
                if (contador_adr == 7 && ~RNW) begin // Si deseo escribir último bit es 0
                    SDA_OUT <= 1'b0; // Enviar 0 si RW ESCRITURA
                end
                contador_adr <= contador_adr + 1; //Contador de bits direcion incrementa en 1.
                
            end

            LECTURA: begin // Lectura
                if (contador_bits <= 15) begin //Cuando leo 15 o menos bits
                    // Desplaza los bits de RD_DATA a la izquierda e inserta el nuevo bit desde SDA_IN
                    RD_DATA <= {RD_DATA[14:0], SDA_IN}; // RDA almacena contenido se SDA_IN
                    SDA_OE <= 0;  // Habilitar la salida SDA
                end
                contador_bits <= contador_bits + 1; // Incrementar el contador de bits
                
            end

            ESCRITURA: begin // Escritura
                // Durante la escritura, envía los bits de WR_DATA por SDA_OUT uno a uno
                if (contador_bits <= 15) begin // Si contador_bits es menor o igual a 15
                    SDA_OUT <= WR_DATA[15 - contador_bits]; // Enviar el bit correspondiente de WR_DATA
                    SDA_OE <= 1;  // Habilitar la salida SDA
                end
                contador_bits <= contador_bits + 1; // Incrementar el contador de bits
            end

            PARADA: begin
                // Lógica para manejar el estado de PARADA
                SDA_OE <= 0;  // Asegurar que la salida esté deshabilitada en PARADA
            end
        endcase
    end
end

endmodule

Tarea4/src/testbench.v
`include "generador.v"
`include "receptor.v"
`include "tester.v"

module comunicacion_tb;
    // Señales de interconexión
    wire clk;
    wire rst;
    wire START_STB;
    wire RNW;
    wire [6:0] I2C_ADDR;
    wire SDA_IN;
    wire [15:0] WR_DATA;
    wire SDA_OE;
    wire SCL;
    wire SDA_OUT;
    wire [15:0] RD_DATA;

    // Instancia del módulo generador de transacciones I2C
    generador_transacciones U0 (
        .clk(clk),
        .rst(rst),
        .START_STB(START_STB),
        .RNW(RNW),
        .I2C_ADDR(I2C_ADDR),
        .SDA_IN(SDA_IN),
        .WR_DATA(WR_DATA),
        .SDA_OE(SDA_OE),
        .SCL(SCL),
        .SDA_OUT(SDA_OUT),
        .RD_DATA(RD_DATA)
    );

    receptor_transacciones U1(
        .clk_receptor(clk),
        .rst_receptor(rst),
        .I2C_ADDR_receptor(I2C_ADDR),
        .SCL(SCL),
        .SDA_OUT(SDA_OUT),
        .SDA_OE(SDA_OE),
        .SDA_IN(SDA_IN),
        .WR_DATA_receptor(WR_DATA),
        .RD_DATA_receptor(RD_DATA)
    );

    // Instancia del módulo tester
    tester_generador T0 (
        .clk(clk),
        .rst(rst),
        .START_STB(START_STB),
        .RNW(RNW),
        .I2C_ADDR(I2C_ADDR),
        .SDA_IN(SDA_IN),
        .WR_DATA(WR_DATA),
        .SDA_OE(SDA_OE),
        .SCL(SCL),
        .SDA_OUT(SDA_OUT),
        .RD_DATA(RD_DATA)
    );

    // Creación del archivo VCD para análisis en GTKWave
    initial begin
        $dumpfile("resultados_generador.vcd");
        $dumpvars(0, comunicacion_tb);
    end
endmodule

Tarea4/src/resultados_generador.vcd
$date
	Tue Oct 15 16:30:10 2024
$end
$version
	Icarus Verilog
$end
$timescale
	1s
$end
$scope module comunicacion_tb $end
$var wire 1 ! SDA_IN $end
$var wire 16 " WR_DATA [15:0] $end
$var wire 1 # rst $end
$var wire 1 $ clk $end
$var wire 1 % START_STB $end
$var wire 1 & SDA_OUT $end
$var wire 1 ' SDA_OE $end
$var wire 1 ( SCL $end
$var wire 1 ) RNW $end
$var wire 16 * RD_DATA [15:0] $end
$var wire 7 + I2C_ADDR [6:0] $end
$scope module T0 $end
$var wire 1 & SDA_OUT $end
$var wire 1 ' SDA_OE $end
$var wire 1 ( SCL $end
$var wire 16 , RD_DATA [15:0] $end
$var reg 7 - I2C_ADDR [6:0] $end
$var reg 1 ) RNW $end
$var reg 1 . SDA_IN $end
$var reg 1 % START_STB $end
$var reg 16 / WR_DATA [15:0] $end
$var reg 1 $ clk $end
$var reg 1 # rst $end
$upscope $end
$scope module U0 $end
$var wire 7 0 I2C_ADDR [6:0] $end
$var wire 1 ) RNW $end
$var wire 1 ! SDA_IN $end
$var wire 1 % START_STB $end
$var wire 16 1 WR_DATA [15:0] $end
$var wire 1 $ clk $end
$var wire 1 # rst $end
$var wire 1 2 clk_div4 $end
$var wire 1 ( SCL $end
$var reg 16 3 RD_DATA [15:0] $end
$var reg 1 ' SDA_OE $end
$var reg 1 & SDA_OUT $end
$var reg 1 4 clk_div2 $end
$var reg 1 5 condicion_scl $end
$var reg 5 6 contador_adr [4:0] $end
$var reg 5 7 contador_bits [4:0] $end
$var reg 2 8 count_clock [1:0] $end
$var reg 1 9 flag_comunicacion $end
$var reg 3 : next_state [2:0] $end
$var reg 3 ; state [2:0] $end
$upscope $end
$scope module U1 $end
$var wire 7 < I2C_ADDR_receptor [6:0] $end
$var wire 16 = RD_DATA_receptor [15:0] $end
$var wire 1 ( SCL $end
$var wire 1 ' SDA_OE $end
$var wire 1 & SDA_OUT $end
$var wire 1 $ clk_receptor $end
$var wire 1 # rst_receptor $end
$var reg 1 > SDA_IN $end
$var reg 16 ? WR_DATA_receptor [15:0] $end
$var reg 5 @ contador_adr_receptor [4:0] $end
$var reg 5 A contador_bits_receptor [4:0] $end
$var reg 1 B flag_comunicacion_receptor $end
$var reg 7 C get_I2C_ADDR [6:0] $end
$var reg 3 D next_state_receptor [2:0] $end
$var reg 3 E state_receptor [2:0] $end
$var reg 1 F ultimo_bit_adr $end
$upscope $end
$upscope $end
$enddefinitions $end
#0
$dumpvars
xF
bx E
bx D
bx C
xB
bx A
bx @
bx ?
x>
bx =
b111101 <
bx ;
bx :
x9
bx 8
bx 7
bx 6
x5
x4
bx 3
x2
bx 1
b111101 0
b1001000110100 /
x.
b111101 -
bx ,
b111101 +
bx *
0)
x(
x'
x&
0%
0$
1#
bx "
x!
$end
#10
0F
b0 C
b0 @
b0 A
1(
02
b0 :
b0 D
05
09
b0 ;
b0 8
04
b0 6
b0 7
1B
1>
b0 E
1$
#20
0$
#25
0#
#30
b1 D
0>
0&
b1 8
14
1$
#40
0$
#50
12
b10 8
04
b1 E
1$
#60
0$
#70
b11 8
14
1$
#75
b1 :
15
1%
#80
0$
#90
0(
02
b1 ;
b0 8
04
1$
#100
0$
#110
b1 8
14
1$
#120
0$
#125
0%
#130
b1 @
b1 6
1(
12
b10 8
04
1$
#140
0$
#150
b11 8
14
1$
#160
0$
#170
0(
02
b0 8
04
1$
#180
0$
#190
b1 8
14
1$
#200
0$
#210
b10 6
1&
b10 @
1(
12
b10 8
04
1$
#220
0$
#230
b11 8
14
1$
#240
0$
#250
0(
02
b0 8
04
1$
#260
0$
#270
b1 8
14
1$
#280
0$
#290
b11 @
1>
b1 C
b11 6
1(
12
b10 8
04
1$
#300
0$
#310
b11 8
14
1$
#320
0$
#330
0(
02
b0 8
04
1$
#340
0$
#350
b1 8
14
1$
#360
0$
#370
b100 6
b100 @
b11 C
1(
12
b10 8
04
1$
#380
0$
#390
b11 8
14
1$
#400
0$
#410
0(
02
b0 8
04
1$
#420
0$
#430
b1 8
14
1$
#440
0$
#450
b101 @
b111 C
b101 6
1(
12
b10 8
04
1$
#460
0$
#470
b11 8
14
1$
#480
0$
#490
0(
02
b0 8
04
1$
#500
0$
#510
b1 8
14
1$
#520
0$
#530
b110 6
0&
b110 @
b1111 C
1(
12
b10 8
04
1$
#540
0$
#550
b11 8
14
1$
#560
0$
#570
0(
02
b0 8
04
1$
#580
0$
#590
b1 8
14
1$
#600
0$
#610
b111 @
0>
b11110 C
b111 6
1&
1(
12
b10 8
04
1$
#620
0$
#630
b11 8
14
1$
#640
0$
#650
0(
02
b0 8
04
1$
#660
0$
#670
b1 8
14
1$
#680
0$
#690
b10 :
b11 D
b1000 6
0&
b1000 @
1>
1F
1(
12
b10 8
04
1$
#700
0$
#710
b100 :
b11 E
b11 8
14
b10 ;
1$
#720
0$
#730
0(
02
b100 ;
b0 8
04
1$
#740
0$
#750
1&
b1 8
14
1$
#760
0$
#770
b1 A
x>
0'
1(
12
b10 8
04
1$
#780
0$
#790
b11 8
14
1$
#800
0$
#810
0(
02
b0 8
04
1$
#820
0$
#830
b1 8
14
1$
#840
0$
#850
b10 A
1(
12
b10 8
04
1$
#860
0$
#870
b11 8
14
1$
#880
0$
#890
0(
02
b0 8
04
1$
#900
0$
#910
b1 8
14
1$
#920
0$
#930
b11 A
1(
12
b10 8
04
1$
#940
0$
#950
b11 8
14
1$
#960
0$
#970
0(
02
b0 8
04
1$
#980
0$
#990
b1 8
14
1$
#1000
0$
#1010
b100 A
1(
12
b10 8
04
1$
#1020
0$
#1030
b11 8
14
1$
#1040
0$
#1050
0(
02
b0 8
04
1$
#1060
0$
#1070
b1 8
14
1$
#1080
0$
#1090
b101 A
1(
12
b10 8
04
1$
#1100
0$
#1110
b11 8
14
1$
